{"results":[[{"type":"string"},{"type":"number"},{"type":"string"},{"type":"number"},{"type":"string"},{"type":"number"},{"type":"string"},{"type":"number"},{"type":"string"},{"type":"number"},{"type":"string"},{"type":"number"},{"type":"string"},{"type":"number"},{"type":"string"},{"type":"number"},{"type":"string"},{"type":"number"},{"type":"string"},{"type":"number"},{"type":"string"},{"type":"number"},{"type":"string"},{"type":"number"},{"type":"string"},{"type":"number"},{"type":"string"},{"type":"number"},{"type":"string"},{"type":"number"},{"type":"string"},{"type":"number"},{"type":"string"},{"type":"number"},{"type":"string"},{"type":"number"},{"type":"string"},{"type":"number"},{"type":"string"},{"type":"number"},{"type":"string"},{"type":"number"},{"type":"string"},{"type":"number"},{"type":"string"},{"type":"number"},{"type":"string"},{"type":"number"},{"type":"string"},{"type":"number"},{"type":"string"},{"type":"number"},{"type":"string"},{"type":"number"},{"type":"string"},{"type":"number"},{"type":"string"},{"type":"number"},{"type":"string"},{"type":"number"},{"type":"string"}],["Weapon Item Level",1953,"1",3906,"2",5861,"3",9130,"4",12399,"5",15670,"6",18084,"7",20498,"8",22912,"9",25498,"10",28084,"11",30670,"12",33650,"13",36630,"14",39612,"15",42758,"16",45904,"17",49051,"18",52261,"19",55471,"20",58683,"21",61019,"22",63355,"23",65693,"24",69706,"25",73719,"26",77732,"27",80609,"28",83486,"29",86363,"30"],["Fortune Strikes",15782,"1",31441,"2",48900,"3",0,"",0,"",0,"",0,"",0,"",0,"",0,"",0,"",0,"",0,"",0,"",0,"",0,"",0,"",0,"",0,"",0,"",0,"",0,"",0,"",0,"",0,"",0,"",0,"",0,"",0,"",0,""],["Shocklight",11250,"1",26087,"2",37777,"3",0,"",0,"",0,"",0,"",0,"",0,"",0,"",0,"",0,"",0,"",0,"",0,"",0,"",0,"",0,"",0,"",0,"",0,"",0,"",0,"",0,"",0,"",0,"",0,"",0,"",0,"",0,""],["Dark Sorrows",18596,"1",40782,"2",61119,"3",0,"",0,"",0,"",0,"",0,"",0,"",0,"",0,"",0,"",0,"",0,"",0,"",0,"",0,"",0,"",0,"",0,"",0,"",0,"",0,"",0,"",0,"",0,"",0,"",0,"",0,"",0,""],["Fatebringer",15821,"1",32334,"2",50415,"3",0,"",0,"",0,"",0,"",0,"",0,"",0,"",0,"",0,"",0,"",0,"",0,"",0,"",0,"",0,"",0,"",0,"",0,"",0,"",0,"",0,"",0,"",0,"",0,"",0,"",0,"",0,""],["Shadowbind",23400,"1",44656,"2",68095,"3",0,"",0,"",0,"",0,"",0,"",0,"",0,"",0,"",0,"",0,"",0,"",0,"",0,"",0,"",0,"",0,"",0,"",0,"",0,"",0,"",0,"",0,"",0,"",0,"",0,"",0,"",0,""],["Black Powder",6048,"1",14414,"2",24733,"3",0,"",0,"",0,"",0,"",0,"",0,"",0,"",0,"",0,"",0,"",0,"",0,"",0,"",0,"",0,"",0,"",0,"",0,"",0,"",0,"",0,"",0,"",0,"",0,"",0,"",0,"",0,""],["Secure in the Light",22656,"1",43873,"2",69508,"3",0,"",0,"",0,"",0,"",0,"",0,"",0,"",0,"",0,"",0,"",0,"",0,"",0,"",0,"",0,"",0,"",0,"",0,"",0,"",0,"",0,"",0,"",0,"",0,"",0,"",0,"",0,""],["Blade Dancer",35556,"1",84762,"2",119774,"3",0,"",0,"",0,"",0,"",0,"",0,"",0,"",0,"",0,"",0,"",0,"",0,"",0,"",0,"",0,"",0,"",0,"",0,"",0,"",0,"",0,"",0,"",0,"",0,"",0,"",0,"",0,""],["Master of Shadows",11522,"1",23303,"2",34886,"3",0,"",0,"",0,"",0,"",0,"",0,"",0,"",0,"",0,"",0,"",0,"",0,"",0,"",0,"",0,"",0,"",0,"",0,"",0,"",0,"",0,"",0,"",0,"",0,"",0,"",0,"",0,""],["Chaotic Darkness",19529,"1",40194,"2",61436,"3",0,"",0,"",0,"",0,"",0,"",0,"",0,"",0,"",0,"",0,"",0,"",0,"",0,"",0,"",0,"",0,"",0,"",0,"",0,"",0,"",0,"",0,"",0,"",0,"",0,"",0,"",0,""],["Torment the Weak",23231,"1",48112,"2",72892,"3",0,"",0,"",0,"",0,"",0,"",0,"",0,"",0,"",0,"",0,"",0,"",0,"",0,"",0,"",0,"",0,"",0,"",0,"",0,"",0,"",0,"",0,"",0,"",0,"",0,"",0,"",0,""],["Fortune's Strike",6314,"1",14865,"2",23818,"3",0,"",0,"",0,"",0,"",0,"",0,"",0,"",0,"",0,"",0,"",0,"",0,"",0,"",0,"",0,"",0,"",0,"",0,"",0,"",0,"",0,"",0,"",0,"",0,"",0,"",0,"",0,""],["Fate's Thirst",12588,"1",25777,"2",40232,"3",0,"",0,"",0,"",0,"",0,"",0,"",0,"",0,"",0,"",0,"",0,"",0,"",0,"",0,"",0,"",0,"",0,"",0,"",0,"",0,"",0,"",0,"",0,"",0,"",0,"",0,"",0,""],["Gunslinger",6877,"1",15184,"2",22557,"3",0,"",0,"",0,"",0,"",0,"",0,"",0,"",0,"",0,"",0,"",0,"",0,"",0,"",0,"",0,"",0,"",0,"",0,"",0,"",0,"",0,"",0,"",0,"",0,"",0,"",0,"",0,""],["Fortune's Boon",20345,"1",35956,"2",50728,"3",0,"",0,"",0,"",0,"",0,"",0,"",0,"",0,"",0,"",0,"",0,"",0,"",0,"",0,"",0,"",0,"",0,"",0,"",0,"",0,"",0,"",0,"",0,"",0,"",0,"",0,"",0,""],["Infusion of Light",22512,"1",45245,"2",67931,"3",0,"",0,"",0,"",0,"",0,"",0,"",0,"",0,"",0,"",0,"",0,"",0,"",0,"",0,"",0,"",0,"",0,"",0,"",0,"",0,"",0,"",0,"",0,"",0,"",0,"",0,"",0,""],["Sabermetrics",9844,"1",23101,"2",35680,"3",0,"",0,"",0,"",0,"",0,"",0,"",0,"",0,"",0,"",0,"",0,"",0,"",0,"",0,"",0,"",0,"",0,"",0,"",0,"",0,"",0,"",0,"",0,"",0,"",0,"",0,"",0,""],["Murderous Intent",16326,"1",33656,"2",51309,"3",0,"",0,"",0,"",0,"",0,"",0,"",0,"",0,"",0,"",0,"",0,"",0,"",0,"",0,"",0,"",0,"",0,"",0,"",0,"",0,"",0,"",0,"",0,"",0,"",0,"",0,"",0,""],["Light Speed",15795,"1",33050,"2",49898,"3",0,"",0,"",0,"",0,"",0,"",0,"",0,"",0,"",0,"",0,"",0,"",0,"",0,"",0,"",0,"",0,"",0,"",0,"",0,"",0,"",0,"",0,"",0,"",0,"",0,"",0,"",0,""],["% DPS Gain",8250,"0.5",16500,"1.0",24750,"1.5",33000,"2.0",41250,"2.5",49500,"3.0",57750,"3.5",66000,"4.0",74250,"4.5",82500,"5.0",90750,"5.5",99000,"6.0",107250,"6.5",115500,"7.0",123750,"7.5",0,"",0,"",0,"",0,"",0,"",0,"",0,"",0,"",0,"",0,"",0,"",0,"",0,"",0,"",0,""]],"metas":{"build_date":"Apr  1 2018","build_time":"16:33:51","git_revision":null,"options":{"debug":false,"max_time":300.0,"expected_iteration_time":240.0,"vary_combat_length":0.2,"iterations":31354,"target_error":0.1,"threads":32,"seed":10274496409880767627,"single_actor_batch":false,"queue_lag":0.005,"queue_lag_stddev":0.001,"gcd_lag":0.15,"gcd_lag_stddev":0.037,"channel_lag":0.25,"channel_lag_stddev":0.062,"queue_gcd_reduction":0.1,"strict_gcd_queue":0,"confidence":0.95,"confidence_estimator":1.9599639854088815,"world_lag":0.1,"world_lag_stddev":0.01,"travel_variance":0.0,"default_skill":1.0,"reaction_time":0.5,"regen_periodicity":0.25,"ignite_sampling_delta":0.2,"fixed_time":false,"optimize_expressions":true,"optimal_raid":1,"log":0,"debug_each":0,"auto_ready_trigger":0,"stat_cache":1,"max_aoe_enemies":20,"show_etmi":false,"tmi_window_global":0.0,"tmi_bin_size":0.5,"enemy_death_pct":0.0,"challenge_mode":false,"timewalk":-1,"pvp_crit":false,"rng":{"name":"sse2-sfmt"},"deterministic":0,"average_range":1,"average_gauss":0,"fight_style":"Patchwerk","default_aura_delay":0.03,"default_aura_delay_stddev":0.005,"dbc":{"Live":{"build_level":25901,"wow_version":"7.3.5"},"version_used":"Live"}},"overrides":{"mortal_wounds":1,"bleeding":1,"bloodlust":1,"bloodlust_percent":25,"bloodlust_time":0.5},"statistics":{"elapsed_cpu_seconds":96.125,"elapsed_time_seconds":3.021185,"init_time_seconds":1.5878122760000002,"merge_time_seconds":0.0068752530000000004,"analyze_time_seconds":0.016004333000000003,"simulation_length":{"sum":9398889.544000005,"count":31322,"mean":300.0730969925294,"min":132.072,"max":441.242,"median":299.071,"variance":2170.2836520231594,"std_dev":46.58630326633741,"mean_variance":0.06928943400878486,"mean_std_dev":0.26322886241593046},"raid_dps":{"sum":51681486546.923325,"count":31322,"mean":1650005.9557794307},"total_dmg":{"sum":15367671436397.824,"count":31322,"mean":490635062.7800851}},"player":{"name":"Template","race":"night_elf","level":110,"role":"attack","specialization":"Outlaw Rogue","talents":[{"tier":1,"id":22120,"spell_id":196938,"name":"Quick Draw"},{"tier":2,"id":19238,"spell_id":196922,"name":"Hit and Run"},{"tier":3,"id":19239,"spell_id":193531,"name":"Deeper Stratagem"},{"tier":6,"id":19249,"spell_id":193539,"name":"Alacrity"},{"tier":7,"id":22133,"spell_id":137619,"name":"Marked for Death"}],"artifact":[{"id":1052,"spell_id":202665,"name":"Curse of the Dreadblades","total_rank":1,"purchased_rank":1,"crucible_rank":0,"relic_rank":0},{"id":1053,"spell_id":202897,"name":"Blunderbuss","total_rank":1,"purchased_rank":1,"crucible_rank":0,"relic_rank":0},{"id":1054,"spell_id":202820,"name":"Greed","total_rank":1,"purchased_rank":1,"crucible_rank":0,"relic_rank":0},{"id":1055,"spell_id":202769,"name":"Blurred Time","total_rank":1,"purchased_rank":1,"crucible_rank":0,"relic_rank":0},{"id":1056,"spell_id":202755,"name":"Deception","total_rank":1,"purchased_rank":1,"crucible_rank":0,"relic_rank":0},{"id":1057,"spell_id":202753,"name":"Hidden Blade","total_rank":1,"purchased_rank":1,"crucible_rank":0,"relic_rank":0},{"id":1058,"spell_id":202628,"name":"Blademaster","total_rank":1,"purchased_rank":1,"crucible_rank":0,"relic_rank":0},{"id":1059,"spell_id":216230,"name":"Black Powder","total_rank":4,"purchased_rank":4,"crucible_rank":0,"relic_rank":0,"override_rank":4},{"id":1060,"spell_id":202507,"name":"Blade Dancer","total_rank":4,"purchased_rank":4,"crucible_rank":0,"relic_rank":0,"override_rank":4},{"id":1061,"spell_id":202514,"name":"Fate's Thirst","total_rank":4,"purchased_rank":4,"crucible_rank":0,"relic_rank":0,"override_rank":4},{"id":1062,"spell_id":202521,"name":"Fortune's Strike","total_rank":4,"purchased_rank":4,"crucible_rank":0,"relic_rank":0,"override_rank":4},{"id":1063,"spell_id":202522,"name":"Gunslinger","total_rank":4,"purchased_rank":4,"crucible_rank":0,"relic_rank":0,"override_rank":4},{"id":1064,"spell_id":202524,"name":"Fatebringer","total_rank":4,"purchased_rank":4,"crucible_rank":0,"relic_rank":0,"override_rank":4},{"id":1065,"spell_id":202530,"name":"Fortune Strikes","total_rank":4,"purchased_rank":4,"crucible_rank":0,"relic_rank":0,"override_rank":4},{"id":1066,"spell_id":202533,"name":"Ghostly Shell","total_rank":4,"purchased_rank":4,"crucible_rank":0,"relic_rank":0,"override_rank":4},{"id":1067,"spell_id":202907,"name":"Fortune's Boon","total_rank":4,"purchased_rank":4,"crucible_rank":0,"relic_rank":0,"override_rank":4},{"id":1348,"spell_id":202463,"name":"Cursed Edges","total_rank":1,"purchased_rank":1,"crucible_rank":0,"relic_rank":0},{"id":1385,"spell_id":214929,"name":"Cursed Steel","total_rank":1,"purchased_rank":1,"crucible_rank":0,"relic_rank":0},{"id":1581,"spell_id":238067,"name":"Sabermetrics","total_rank":4,"purchased_rank":4,"crucible_rank":0,"relic_rank":0,"override_rank":4},{"id":1582,"spell_id":238103,"name":"Dreadblade's Vigor","total_rank":1,"purchased_rank":1,"crucible_rank":0,"relic_rank":0},{"id":1583,"spell_id":238139,"name":"Loaded Dice","total_rank":1,"purchased_rank":1,"crucible_rank":0,"relic_rank":0},{"id":1584,"spell_id":239042,"name":"Concordance of the Legionfall","total_rank":24,"purchased_rank":24,"crucible_rank":0,"relic_rank":0},{"id":1652,"spell_id":241153,"name":"Bravado of the Uncrowned","total_rank":1,"purchased_rank":1,"crucible_rank":0,"relic_rank":0}],"party":0,"ready_type":1,"bugs":true,"scale_player":true,"potion_used":false,"timeofday":"DAY_TIME","invert_scaling":0,"reaction_offset":0.1,"reaction_max":1.4000000000000001,"reaction_mean":0.3,"reaction_stddev":0.06,"reaction_nu":0.25,"world_lag":0.1,"brain_lag":0.0,"brain_lag_stddev":0.0,"world_lag_override":false,"world_lag_stddev_override":false,"dbc":{"Live":{"build_level":25901,"wow_version":"7.3.5"},"version_used":"Live"},"base_energy_regen_per_second":12.0,"collected_data":{"fight_length":{"sum":9398889.544,"count":31322,"mean":300.0730969925292,"min":132.072,"max":441.242},"waiting_time":{"sum":1332947.56,"count":31322,"mean":42.556272268692936,"min":3.567,"max":92.315},"executed_foreground_actions":{"sum":10239169.0,"count":31322,"mean":326.90022987037867,"min":189.0,"max":446.0},"dmg":{"sum":15367671436397.824,"count":31322,"mean":490635062.7800851,"min":381553518.17422163,"max":601116035.4495494},"compound_dmg":{"sum":15367671436397.824,"count":31322,"mean":490635062.7800851,"min":381553518.17422163,"max":601116035.4495494},"timeline_dmg":{"mean":1561979.573124758,"mean_std_dev":392425.61696850037,"min":144285.5365226609,"max":4628318.257276555,"data":[2445080.141470851,2302987.7849146696,4628318.257276555,2686177.1346641933,3838863.204222611,3151995.265883866,3682386.7658692114,4188877.476577728,3015294.120543947,4033089.795400226,3910394.1549030608,2384241.802913934,2190724.717004616,1869148.513784242,2153439.119854447,1896648.5252656327,1748820.5599528376,2017213.299404577,2203395.172028465,2078357.5329505757,2011275.7825733055,2223165.082571163,2207588.6951175053,2037506.8153242152,2103011.328038078,2211605.074864785,2270639.748555986,2232546.3512315517,2215435.3548036637,1931309.5640662713,1819525.1639928177,1733212.397367948,1685908.4903487384,1686290.9959258353,1681737.1782315767,1633461.936758748,1658796.0557298055,1622765.1493414368,1647655.1475581722,1578607.2240751842,1614585.0353182135,1517404.6412926917,1523014.838841096,1478644.9154157378,1208404.8507972527,2077712.2230275054,1901160.6454271404,1907742.3256010965,1906411.7169922004,1381487.8952607736,1372362.1216647045,1346638.1686124573,1228768.317266983,1051261.0447455533,1163457.8841554965,1289380.6812788902,1403014.2510252688,1281879.1989616372,1858880.011919285,1674333.600942469,1729800.2039737264,1695625.26607102,1883065.9068748485,1820014.0139295205,1823397.9074585966,1765520.7021029452,1822206.1952717432,1761019.9220406031,1766178.7089425789,1704968.1162631672,1705525.5610253036,1669163.5612774643,1627152.3333667803,1579421.4798214296,1583122.959881573,1554469.9316795997,1506007.2944197431,1494750.1628060467,1482346.290138864,1485123.4908462418,1510845.248610524,1512897.0383252106,1526827.6589216676,1574791.8106352957,1599240.3592944504,1632619.4575830803,1631844.2962878018,1657571.5666956725,1587944.6169099323,1408497.3403692194,1942174.49587743,1933090.7513900436,1926598.9372258098,1908312.3524274412,1559710.6104959496,1417810.7927112454,1404113.85107785,1401825.893151346,1417868.0742755146,1419261.327164119,1429718.5942936526,1409357.667522511,1415137.6851515952,1410696.959132837,1422129.2256192516,1417598.077657402,1418981.1452661052,1423614.9401375486,1425218.7271834563,1421812.1247198102,1438929.1193104354,1442480.7787452247,1470007.2933817997,1496068.0116708963,1520273.139096229,1540845.8131635268,1577757.8243807303,1601518.0898764639,1600009.8881378216,1602473.415390994,1614862.59456003,1655105.577107003,1656121.0489664748,1663139.2821057732,1680705.866902795,1692917.1967561925,1689546.356258025,1688838.90086882,1664613.1983101007,1662908.2997003926,1633053.060965913,1586263.59591014,1550474.6336784873,1552061.1321406914,1515740.3738120554,1732314.7783963555,1743289.115824395,1727300.6963472932,1720266.0826132037,1542962.233915923,1518396.4573901645,1495097.9227653898,1488114.2816899698,1472584.4741279352,1459797.8616834164,1446422.4720393047,1428860.267526701,1423218.5267698148,1399834.21159178,1384644.9434106837,1387725.749359622,1369619.5919466354,1372524.7550244224,1359793.6839015386,1362196.9443237304,1353603.1444044851,1357813.1302389766,1361636.6511805707,1368118.3981343627,1350276.4489079851,1358982.9122058172,1358561.2301094516,1361883.8144913712,1380389.0182447403,1395295.2627589984,1422550.6887700055,1419209.750543972,1440073.1532625116,1435846.8729819595,1467862.2321474957,1471017.5896391002,1491048.4712239043,1486956.492826426,1483529.2343679136,1492123.0631254353,1536875.608343608,1531084.8617110956,1530350.250448256,1525034.8294765092,1506696.8582886301,1632272.9908943214,1692445.8831072503,1697027.8790144015,1727073.2633532216,1630110.7106207593,1588264.7490207278,1592646.0418955537,1592487.141951053,1587344.4646609274,1593468.2645882678,1581263.994046321,1570244.1383992278,1567841.9953555826,1563596.6588667622,1559601.6260076466,1547175.9896822183,1530777.4451408861,1536276.3539538519,1543176.0105233267,1532279.4353134225,1535966.1070974164,1540277.6007856617,1526522.090185671,1536356.1469825145,1529860.1247459576,1529053.714928372,1540016.9825611883,1523478.3062227163,1504594.8853899022,1509310.9833228246,1484710.072096653,1483603.9224441773,1492750.2283708563,1472607.5789551204,1474984.4962775144,1456145.683811818,1448278.2299253892,1436768.582461109,1422466.040420824,1415700.1897562193,1427458.833158926,1398993.1293163595,1394348.2295169071,1403834.7036879703,1390293.7876331618,1468972.5536706154,1515411.895168796,1532878.498496728,1554518.9473800962,1499254.3108174421,1459777.681817742,1463681.5076299082,1457269.4913259724,1452854.9799367322,1456280.8453700934,1460245.122240369,1452177.7141752376,1465933.343744482,1465159.0439914588,1462080.3749650377,1478988.2918105857,1467244.815300017,1451866.1841759603,1467861.9979448137,1467524.3997060168,1477760.9087725452,1480989.5009633147,1494040.0439080934,1514459.091299441,1516842.0854312608,1530826.9523872628,1527809.0201148437,1535459.3260969394,1539295.5773869867,1524690.275092786,1539225.769640935,1543250.7911087628,1524642.3526570036,1522314.5831419972,1535034.9117090637,1519392.7972220078,1509602.8579069038,1506016.8456314532,1475758.6640691254,1472323.9116084932,1466277.3646316815,1458440.8425531853,1464675.0582255607,1453047.5070874942,1448056.796576038,1480779.6203564887,1530208.9520843364,1555183.1250514765,1548964.5053540661,1535187.9576274597,1496681.6812404408,1497875.3755846792,1502698.527667833,1482409.2005240242,1491506.7891880784,1486508.5958706941,1474179.0717742492,1486139.6961178158,1479450.826216475,1465943.4268801298,1479374.5768929566,1466838.0637775261,1466370.2536737276,1478430.4589823869,1489518.6874604623,1480794.1306999135,1489864.1096956022,1509021.9581685208,1487862.85049196,1511808.0212009652,1505561.5920716415,1501213.0451524197,1519178.6300125394,1505350.962640178,1537204.3723310076,1496860.2634655768,1509463.8992274583,1483514.591541146,1490615.812555538,1492994.923609631,1515111.2297602692,1499686.9885664554,1483835.182913986,1494346.3777197427,1504661.4801350574,1482246.2371723375,1478000.261753652,1485632.7664265158,1487268.7401255793,1472832.5909277364,1482213.0388448567,1534559.5247240043,1525187.1147333893,1560180.0534809544,1527455.349392689,1499738.6647500522,1515567.289877912,1486238.1267898616,1494721.6851611205,1494434.5215687635,1486841.6585244325,1478822.4594706446,1467476.602722581,1477662.4706349347,1477210.9118113415,1465151.3992482217,1471887.5429178576,1450250.9788898835,1450643.2222730322,1442794.5969814213,1452389.9359631797,1457139.6875800083,1443467.7368371047,1464783.4953545309,1451756.315996917,1470416.567480325,1460159.0186210375,1442824.1118015733,1451539.6023304132,1453062.0969063237,1427399.6915312565,1417497.0055836074,1438627.483428866,1437294.367618284,1406228.8102455258,1397367.499963947,1380960.1375258048,1424214.327492518,1412690.2542505912,1400948.8704249372,1393963.6849431887,1390942.9687425396,1399053.9441415104,1412643.0327293605,1384330.0407687395,1388065.2392125935,1431518.3549724675,1422970.144734868,1454008.5635831563,1427736.0269698324,1450297.044634592,1433790.8904346572,1441931.5396595069,1427383.044500027,1452533.2709490664,1459119.3358959483,1432761.8795524142,1453118.6278602777,1448422.2198645838,1402224.8365015713,1435177.2891826543,1477444.5591162606,1476725.182925257,1477026.3696705354,1401183.7810813645,1436565.144072502,1425422.0997963068,1422495.6660241291,1429314.9038827,1466978.7237714587,1461534.1055411866,1389849.7694474775,1377339.1072208865,1315758.879725564,1403322.1451626709,1419952.497978391,1431958.025136686,1538820.7347928642,1344140.8123673266,1360467.6398727219,1499728.7388377814,1336013.3217018005,1341672.0563083503,1359582.0768780364,1365048.9257670697,1361525.7703974715,1338891.2935751886,1517062.452542111,1419508.6896921422,1349435.8085560156,1510602.8052200084,1242453.7813442599,1455993.2396977944,1265785.8448408865,1318824.2606535014,1181448.6083930295,1392686.9277259784,1336249.0547514437,1550211.1903662656,1297205.547727611,1390024.0179916148,1345146.5396957444,1286973.077727266,1288386.5250878162,1002741.823908911,1336698.1556959276,1207764.0835080715,1156608.2953350218,974746.4458451374,1584485.4704911707,1380495.8533325025,960037.4186815838,1443733.612618623,1391387.3163215362,1107069.3607666409,1269255.3619190548,1524959.713420486,2324994.4044447825,1811421.912525845,1094279.0674280138,639248.1933588315,525137.327306117,2978085.1117939223,1109447.1625642302,686990.4859476713,1419857.9688451076,144285.5365226609]},"prioritydps":{"sum":42107042672.33884,"count":31322,"mean":1344328.0337251402,"min":1041300.2256011302,"max":2461306.0700808847,"median":1322634.982293221,"variance":16314645471.307913,"std_dev":127728.79656251331,"mean_variance":520868.57388761616,"mean_std_dev":721.7122514462507},"dps":{"sum":51681486546.92288,"count":31322,"mean":1650005.9557794165,"min":1288396.5133487352,"max":2945059.894907261,"median":1623956.4173085222,"variance":22151265866.718422,"std_dev":148833.01336302515,"mean_variance":707211.0933758515,"mean_std_dev":840.9584373652788},"dpse":{"sum":51681486546.923325,"count":31322,"mean":1650005.9557794307,"min":1288396.5133487352,"max":2945059.894907261},"target_metric":{"sum":51630232401.80592,"count":31322,"mean":1650002.633402765,"min":1288396.5133487352,"max":2945059.894907261,"median":0.0,"variance":22158995005.488937,"std_dev":148858.97690595934,"mean_variance":708158.7359141266,"mean_std_dev":841.521678814115},"buffed_stats":{"attribute":{"strength":8802.0,"agility":44996.0,"stamina":77092.0,"intellect":5325.0},"resources":{"energy":100.0,"combo_points":6.0},"stats":{"attack_power":67494.0,"spell_crit":0.29625,"attack_crit":0.29625,"spell_haste":0.8141554494138081,"attack_haste":0.8141554494138081,"spell_speed":0.8141554494138081,"attack_speed":0.8141554494138081,"mastery_value":0.48818000000000006,"damage_versatility":0.10343157894736842,"heal_versatility":0.10343157894736842,"mitigation_versatility":0.05171578947368421,"crit_rating":7450.0,"crit_pct":0.29625,"haste_rating":8560.0,"haste_pct":0.22826666666666662,"mastery_rating":5674.0,"mastery_pct":0.48818000000000006,"versatility_rating":4913.0,"versatility_pct":0.10343157894736842,"speed_pct":9.24,"armor":2723.0,"dodge":0.2924539881245728,"parry":0.03}}},"gear":{"head":{"name":"fanged_slayers_helm","encoded_item":"fanged_slayers_helm,id=147172,bonus_id=1512/3563","ilevel":930,"stamina":4305,"agiint":2870,"haste_rating":1162,"versatility_rating":686},"neck":{"name":"string_of_extracted_incisors","encoded_item":"string_of_extracted_incisors,id=147013,bonus_id=1512/3563,enchant=mark_of_the_hidden_satyr","ilevel":930,"stamina":2422,"haste_rating":2112,"versatility_rating":1408},"shoulders":{"name":"mantle_of_the_master_assassin","encoded_item":"mantle_of_the_master_assassin,id=144236,bonus_id=3570","ilevel":970,"stamina":4687,"agiint":3124,"haste_rating":460,"mastery_rating":1150},"chest":{"name":"fanged_slayers_chestguard","encoded_item":"fanged_slayers_chestguard,id=147169,bonus_id=1512/3563","ilevel":930,"stamina":4305,"agiint":2870,"crit_rating":1202,"mastery_rating":647},"waist":{"name":"waistguard_of_profane_duplicity","encoded_item":"waistguard_of_profane_duplicity,id=147347,bonus_id=1522/3563","ilevel":940,"stamina":3544,"agiint":2362,"mastery_rating":843,"haste_rating":596},"legs":{"name":"fanged_slayers_legguards","encoded_item":"fanged_slayers_legguards,id=147173,bonus_id=1512/3563","ilevel":930,"stamina":4305,"agiint":2870,"mastery_rating":1241,"haste_rating":607},"feet":{"name":"felscape_pathfinders","encoded_item":"felscape_pathfinders,id=147030,bonus_id=1512/3563","ilevel":930,"stamina":3229,"agiint":2153,"versatility_rating":842,"mastery_rating":545},"wrists":{"name":"greenskins_waterlogged_wristcuffs","encoded_item":"greenskins_waterlogged_wristcuffs,id=137099,bonus_id=3570","ilevel":970,"stamina":3515,"agiint":2343,"crit_rating":690,"haste_rating":517},"hands":{"name":"fanged_slayers_handguards","encoded_item":"fanged_slayers_handguards,id=147171,bonus_id=1512/3563","ilevel":930,"stamina":3229,"agiint":2153,"versatility_rating":871,"crit_rating":515},"finger1":{"name":"yathaes_thumb_ring","encoded_item":"yathaes_thumb_ring,id=147021,bonus_id=1512/3563,enchant=binding_of_haste","ilevel":930,"stamina":2422,"crit_rating":2414,"versatility_rating":1106},"finger2":{"name":"seal_of_the_second_duumvirate","encoded_item":"seal_of_the_second_duumvirate,id=147195,bonus_id=3563/1522,enchant=binding_of_haste","ilevel":940,"stamina":2658,"haste_rating":2030,"crit_rating":1709},"trinket1":{"name":"specter_of_betrayal","encoded_item":"specter_of_betrayal,id=151190,bonus_id=1522/3563","ilevel":940,"stragi":2994},"trinket2":{"name":"convergence_of_fates","encoded_item":"convergence_of_fates,id=140806,bonus_id=3518/1502","ilevel":905,"stragi":2702},"back":{"name":"cloak_of_stifling_brimstone","encoded_item":"cloak_of_stifling_brimstone,id=146984,bonus_id=1512/3563,enchant=binding_of_agility","ilevel":930,"stamina":2422,"stragiint":1615,"haste_rating":676,"mastery_rating":364},"main_hand":{"name":"the_dreadblades","encoded_item":"the_dreadblades,id=128872,bonus_id=742,ilevel=966","ilevel":966,"agility":1720,"stamina":2580,"crit_rating":460,"mastery_rating":442},"off_hand":{"name":"the_dreadblades","encoded_item":"the_dreadblades,id=134552","ilevel":966,"agility":1720,"stamina":2580,"crit_rating":460,"mastery_rating":442}},"custom":{}},"profilesets_overrides":{},"build_timestamp":1522593231,"result_timestamp":1522728503,"crucibleweight":"cruweight^128872^ilvl^1^202530^8.08 6:8.02 7:8.94^252799^5.76^252922^9.52^202524^8.1 6:8.46 7:9.26^252875^11.98^216230^3.1 6:4.28 7:5.28^253070^11.6^202507^18.21 6:25.2 7:17.93^252091^5.9^252888^10.0^252906^11.9^202521^3.23 6:4.38 7:4.58^202514^6.45 6:6.75 7:7.4^202522^3.52 6:4.25 7:3.78^202907^10.42 6:7.99 7:7.56^253093^11.53^238067^5.04 6:6.79 7:6.44^252191^8.36^252088^8.09^end"}}