[[{"type":"string"},{"type":"number"},{"type":"string"},{"type":"number"},{"type":"string"},{"type":"number"},{"type":"string"},{"type":"number"},{"type":"string"},{"type":"number"},{"type":"string"},{"type":"number"},{"type":"string"},{"type":"number"},{"type":"string"},{"type":"number"},{"type":"string"},{"type":"number"},{"type":"string"},{"type":"number"},{"type":"string"},{"type":"number"},{"type":"string"},{"type":"number"},{"type":"string"}],["Weapon Item Level",5461,"1",10922,"2",16384,"3",21792,"4",27200,"5",32609,"6",37853,"7",43097,"8",48341,"9",54005,"10",59669,"11",65333,"12"],["Flames of Sargeras",6433,"1",13801,"2",20399,"3",0,"",0,"",0,"",0,"",0,"",0,"",0,"",0,"",0,""],["Shocklight",14883,"1",30474,"2",46120,"3",0,"",0,"",0,"",0,"",0,"",0,"",0,"",0,"",0,""],["Dark Sorrows",8194,"1",16091,"2",24264,"3",0,"",0,"",0,"",0,"",0,"",0,"",0,"",0,"",0,""],["Master of Disaster",4534,"1",9068,"2",12634,"3",0,"",0,"",0,"",0,"",0,"",0,"",0,"",0,"",0,""],["Shadowbind",17319,"1",34985,"2",52127,"3",0,"",0,"",0,"",0,"",0,"",0,"",0,"",0,"",0,""],["Residual Flames",6617,"1",12607,"2",19322,"3",0,"",0,"",0,"",0,"",0,"",0,"",0,"",0,"",0,""],["Chaotic Darkness",16115,"1",31488,"2",47381,"3",0,"",0,"",0,"",0,"",0,"",0,"",0,"",0,"",0,""],["Master of Shadows",14865,"1",28787,"2",44084,"3",0,"",0,"",0,"",0,"",0,"",0,"",0,"",0,"",0,""],["Soulsnatcher",4397,"1",8271,"2",12550,"3",0,"",0,"",0,"",0,"",0,"",0,"",0,"",0,"",0,""],["Chaotic Instability",8986,"1",18202,"2",27596,"3",0,"",0,"",0,"",0,"",0,"",0,"",0,"",0,"",0,""],["Fire and the Flames",4660,"1",9433,"2",14771,"3",0,"",0,"",0,"",0,"",0,"",0,"",0,"",0,"",0,""],["Torment the Weak",18792,"1",37813,"2",56423,"3",0,"",0,"",0,"",0,"",0,"",0,"",0,"",0,"",0,""],["Burning Hunger",8595,"1",17445,"2",25677,"3",0,"",0,"",0,"",0,"",0,"",0,"",0,"",0,"",0,""],["Murderous Intent",14453,"1",28868,"2",44096,"3",0,"",0,"",0,"",0,"",0,"",0,"",0,"",0,"",0,""],["Light Speed",15334,"1",28716,"2",45082,"3",0,"",0,"",0,"",0,"",0,"",0,"",0,"",0,"",0,""],["Secure in the Light",17778,"1",35267,"2",53016,"3",0,"",0,"",0,"",0,"",0,"",0,"",0,"",0,"",0,""],["Infusion of Light",17699,"1",35314,"2",52563,"3",0,"",0,"",0,"",0,"",0,"",0,"",0,"",0,"",0,""],["% DPS Gain",7008,"0.5",14017,"1.0",21025,"1.5",28034,"2.0",35042,"2.5",42050,"3.0",49059,"3.5",56067,"4.0",63075,"4.5",70084,"5.0",0,"",0,""]]