[[{"type":"string"},{"type":"number"},{"type":"string"},{"type":"number"},{"type":"string"},{"type":"number"},{"type":"string"},{"type":"number"},{"type":"string"},{"type":"number"},{"type":"string"},{"type":"number"},{"type":"string"},{"type":"number"},{"type":"string"},{"type":"number"},{"type":"string"},{"type":"number"},{"type":"string"},{"type":"number"},{"type":"string"},{"type":"number"},{"type":"string"},{"type":"number"},{"type":"string"},{"type":"number"},{"type":"string"},{"type":"number"},{"type":"string"},{"type":"number"},{"type":"string"},{"type":"number"},{"type":"string"},{"type":"number"},{"type":"string"},{"type":"number"},{"type":"string"},{"type":"number"},{"type":"string"},{"type":"number"},{"type":"string"},{"type":"number"},{"type":"string"},{"type":"number"},{"type":"string"},{"type":"number"},{"type":"string"},{"type":"number"},{"type":"string"},{"type":"number"},{"type":"string"},{"type":"number"},{"type":"string"},{"type":"number"},{"type":"string"},{"type":"number"},{"type":"string"},{"type":"number"},{"type":"string"},{"type":"number"},{"type":"string"}],["Weapon Item Level",2359,"1",4718,"2",7079,"3",8777,"4",10475,"5",12174,"6",14676,"7",17178,"8",19682,"9",21998,"10",24314,"11",26632,"12",29221,"13",31810,"14",34399,"15",36589,"16",38779,"17",40969,"18",43802,"19",46635,"20",49470,"21",51677,"22",53884,"23",56091,"24",58708,"25",61325,"26",63943,"27",66511,"28",69079,"29",71649,"30"],["Shocklight",22028,"1",44570,"2",66371,"3",0,"",0,"",0,"",0,"",0,"",0,"",0,"",0,"",0,"",0,"",0,"",0,"",0,"",0,"",0,"",0,"",0,"",0,"",0,"",0,"",0,"",0,"",0,"",0,"",0,"",0,"",0,""],["Dark Sorrows",8471,"1",15858,"2",25619,"3",0,"",0,"",0,"",0,"",0,"",0,"",0,"",0,"",0,"",0,"",0,"",0,"",0,"",0,"",0,"",0,"",0,"",0,"",0,"",0,"",0,"",0,"",0,"",0,"",0,"",0,"",0,""],["Shadowbind",19093,"1",35699,"2",54654,"3",0,"",0,"",0,"",0,"",0,"",0,"",0,"",0,"",0,"",0,"",0,"",0,"",0,"",0,"",0,"",0,"",0,"",0,"",0,"",0,"",0,"",0,"",0,"",0,"",0,"",0,"",0,""],["Master Assassin",19310,"1",23733,"2",53236,"3",0,"",0,"",0,"",0,"",0,"",0,"",0,"",0,"",0,"",0,"",0,"",0,"",0,"",0,"",0,"",0,"",0,"",0,"",0,"",0,"",0,"",0,"",0,"",0,"",0,"",0,"",0,""],["Serrated Edge",4164,"1",8472,"2",13365,"3",0,"",0,"",0,"",0,"",0,"",0,"",0,"",0,"",0,"",0,"",0,"",0,"",0,"",0,"",0,"",0,"",0,"",0,"",0,"",0,"",0,"",0,"",0,"",0,"",0,"",0,"",0,""],["Toxic Blades",9164,"1",20130,"2",28334,"3",0,"",0,"",0,"",0,"",0,"",0,"",0,"",0,"",0,"",0,"",0,"",0,"",0,"",0,"",0,"",0,"",0,"",0,"",0,"",0,"",0,"",0,"",0,"",0,"",0,"",0,"",0,""],["Infusion of Light",18505,"1",37676,"2",54766,"3",0,"",0,"",0,"",0,"",0,"",0,"",0,"",0,"",0,"",0,"",0,"",0,"",0,"",0,"",0,"",0,"",0,"",0,"",0,"",0,"",0,"",0,"",0,"",0,"",0,"",0,"",0,""],["Master Alchemist",19680,"1",40527,"2",59409,"3",0,"",0,"",0,"",0,"",0,"",0,"",0,"",0,"",0,"",0,"",0,"",0,"",0,"",0,"",0,"",0,"",0,"",0,"",0,"",0,"",0,"",0,"",0,"",0,"",0,"",0,"",0,""],["Balanced Blades",6480,"1",12486,"2",17761,"3",0,"",0,"",0,"",0,"",0,"",0,"",0,"",0,"",0,"",0,"",0,"",0,"",0,"",0,"",0,"",0,"",0,"",0,"",0,"",0,"",0,"",0,"",0,"",0,"",0,"",0,"",0,""],["Light Speed",12677,"1",24046,"2",38386,"3",0,"",0,"",0,"",0,"",0,"",0,"",0,"",0,"",0,"",0,"",0,"",0,"",0,"",0,"",0,"",0,"",0,"",0,"",0,"",0,"",0,"",0,"",0,"",0,"",0,"",0,"",0,""],["Strangler",5496,"1",6594,"2",10528,"3",0,"",0,"",0,"",0,"",0,"",0,"",0,"",0,"",0,"",0,"",0,"",0,"",0,"",0,"",0,"",0,"",0,"",0,"",0,"",0,"",0,"",0,"",0,"",0,"",0,"",0,"",0,""],["Gushing Wound",5953,"1",13058,"2",19693,"3",0,"",0,"",0,"",0,"",0,"",0,"",0,"",0,"",0,"",0,"",0,"",0,"",0,"",0,"",0,"",0,"",0,"",0,"",0,"",0,"",0,"",0,"",0,"",0,"",0,"",0,"",0,""],["Murderous Intent",20723,"1",40442,"2",60248,"3",0,"",0,"",0,"",0,"",0,"",0,"",0,"",0,"",0,"",0,"",0,"",0,"",0,"",0,"",0,"",0,"",0,"",0,"",0,"",0,"",0,"",0,"",0,"",0,"",0,"",0,"",0,""],["Chaotic Darkness",16166,"1",32363,"2",48288,"3",0,"",0,"",0,"",0,"",0,"",0,"",0,"",0,"",0,"",0,"",0,"",0,"",0,"",0,"",0,"",0,"",0,"",0,"",0,"",0,"",0,"",0,"",0,"",0,"",0,"",0,"",0,""],["Master of Shadows",23673,"1",47131,"2",71477,"3",0,"",0,"",0,"",0,"",0,"",0,"",0,"",0,"",0,"",0,"",0,"",0,"",0,"",0,"",0,"",0,"",0,"",0,"",0,"",0,"",0,"",0,"",0,"",0,"",0,"",0,"",0,""],["Torment the Weak",19733,"1",39476,"2",58721,"3",0,"",0,"",0,"",0,"",0,"",0,"",0,"",0,"",0,"",0,"",0,"",0,"",0,"",0,"",0,"",0,"",0,"",0,"",0,"",0,"",0,"",0,"",0,"",0,"",0,"",0,"",0,""],["Secure in the Light",18762,"1",37689,"2",54777,"3",0,"",0,"",0,"",0,"",0,"",0,"",0,"",0,"",0,"",0,"",0,"",0,"",0,"",0,"",0,"",0,"",0,"",0,"",0,"",0,"",0,"",0,"",0,"",0,"",0,"",0,"",0,""],["% DPS Gain",9761,"0.5",19521,"1.0",29282,"1.5",39043,"2.0",48804,"2.5",58564,"3.0",68325,"3.5",78086,"4.0",0,"",0,"",0,"",0,"",0,"",0,"",0,"",0,"",0,"",0,"",0,"",0,"",0,"",0,"",0,"",0,"",0,"",0,"",0,"",0,"",0,"",0,""]]