[[{"type":"string"},{"type":"number"},{"type":"string"},{"type":"number"},{"type":"string"},{"type":"number"},{"type":"string"},{"type":"number"},{"type":"string"},{"type":"number"},{"type":"string"},{"type":"number"},{"type":"string"},{"type":"number"},{"type":"string"},{"type":"number"},{"type":"string"},{"type":"number"},{"type":"string"},{"type":"number"},{"type":"string"},{"type":"number"},{"type":"string"},{"type":"number"},{"type":"string"},{"type":"number"},{"type":"string"},{"type":"number"},{"type":"string"},{"type":"number"},{"type":"string"},{"type":"number"},{"type":"string"},{"type":"number"},{"type":"string"},{"type":"number"},{"type":"string"},{"type":"number"},{"type":"string"},{"type":"number"},{"type":"string"},{"type":"number"},{"type":"string"},{"type":"number"},{"type":"string"},{"type":"number"},{"type":"string"},{"type":"number"},{"type":"string"},{"type":"number"},{"type":"string"},{"type":"number"},{"type":"string"},{"type":"number"},{"type":"string"}],["Weapon Item Level",2685,"1",5370,"2",8057,"3",11100,"4",14143,"5",17187,"6",19796,"7",22405,"8",25014,"9",28108,"10",31202,"11",34296,"12",37218,"13",40140,"14",43063,"15",46279,"16",49495,"17",52711,"18",55955,"19",59199,"20",62443,"21",65640,"22",68837,"23",72036,"24",75364,"25",78692,"26",82021,"27"],["Shocklight",22714,"1",47271,"2",70297,"3",0,"",0,"",0,"",0,"",0,"",0,"",0,"",0,"",0,"",0,"",0,"",0,"",0,"",0,"",0,"",0,"",0,"",0,"",0,"",0,"",0,"",0,"",0,"",0,""],["Dark Sorrows",10991,"1",22256,"2",33034,"3",0,"",0,"",0,"",0,"",0,"",0,"",0,"",0,"",0,"",0,"",0,"",0,"",0,"",0,"",0,"",0,"",0,"",0,"",0,"",0,"",0,"",0,"",0,"",0,""],["Wilderness Expert",5651,"1",11788,"2",17786,"3",0,"",0,"",0,"",0,"",0,"",0,"",0,"",0,"",0,"",0,"",0,"",0,"",0,"",0,"",0,"",0,"",0,"",0,"",0,"",0,"",0,"",0,"",0,"",0,""],["Shadowbind",23987,"1",48004,"2",72089,"3",0,"",0,"",0,"",0,"",0,"",0,"",0,"",0,"",0,"",0,"",0,"",0,"",0,"",0,"",0,"",0,"",0,"",0,"",0,"",0,"",0,"",0,"",0,"",0,""],["Pack Leader",13696,"1",28954,"2",43284,"3",0,"",0,"",0,"",0,"",0,"",0,"",0,"",0,"",0,"",0,"",0,"",0,"",0,"",0,"",0,"",0,"",0,"",0,"",0,"",0,"",0,"",0,"",0,"",0,""],["Chaotic Darkness",21060,"1",43475,"2",64663,"3",0,"",0,"",0,"",0,"",0,"",0,"",0,"",0,"",0,"",0,"",0,"",0,"",0,"",0,"",0,"",0,"",0,"",0,"",0,"",0,"",0,"",0,"",0,"",0,""],["Master of Shadows",22002,"1",43119,"2",65712,"3",0,"",0,"",0,"",0,"",0,"",0,"",0,"",0,"",0,"",0,"",0,"",0,"",0,"",0,"",0,"",0,"",0,"",0,"",0,"",0,"",0,"",0,"",0,"",0,""],["Spitting Cobras",8502,"1",20112,"2",28772,"3",0,"",0,"",0,"",0,"",0,"",0,"",0,"",0,"",0,"",0,"",0,"",0,"",0,"",0,"",0,"",0,"",0,"",0,"",0,"",0,"",0,"",0,"",0,"",0,""],["Torment the Weak",26274,"1",52038,"2",77291,"3",0,"",0,"",0,"",0,"",0,"",0,"",0,"",0,"",0,"",0,"",0,"",0,"",0,"",0,"",0,"",0,"",0,"",0,"",0,"",0,"",0,"",0,"",0,"",0,""],["Jaws of Thunder",18345,"1",37400,"2",55713,"3",0,"",0,"",0,"",0,"",0,"",0,"",0,"",0,"",0,"",0,"",0,"",0,"",0,"",0,"",0,"",0,"",0,"",0,"",0,"",0,"",0,"",0,"",0,"",0,""],["Unleash the Beast",14715,"1",30680,"2",45861,"3",0,"",0,"",0,"",0,"",0,"",0,"",0,"",0,"",0,"",0,"",0,"",0,"",0,"",0,"",0,"",0,"",0,"",0,"",0,"",0,"",0,"",0,"",0,"",0,""],["Slithering Serpents",20249,"1",37010,"2",55855,"3",0,"",0,"",0,"",0,"",0,"",0,"",0,"",0,"",0,"",0,"",0,"",0,"",0,"",0,"",0,"",0,"",0,"",0,"",0,"",0,"",0,"",0,"",0,"",0,""],["Light Speed",20451,"1",39682,"2",61522,"3",0,"",0,"",0,"",0,"",0,"",0,"",0,"",0,"",0,"",0,"",0,"",0,"",0,"",0,"",0,"",0,"",0,"",0,"",0,"",0,"",0,"",0,"",0,"",0,""],["Murderous Intent",19030,"1",38178,"2",55785,"3",0,"",0,"",0,"",0,"",0,"",0,"",0,"",0,"",0,"",0,"",0,"",0,"",0,"",0,"",0,"",0,"",0,"",0,"",0,"",0,"",0,"",0,"",0,"",0,""],["Secure in the Light",24760,"1",48215,"2",72650,"3",0,"",0,"",0,"",0,"",0,"",0,"",0,"",0,"",0,"",0,"",0,"",0,"",0,"",0,"",0,"",0,"",0,"",0,"",0,"",0,"",0,"",0,"",0,"",0,""],["Infusion of Light",24194,"1",48924,"2",73206,"3",0,"",0,"",0,"",0,"",0,"",0,"",0,"",0,"",0,"",0,"",0,"",0,"",0,"",0,"",0,"",0,"",0,"",0,"",0,"",0,"",0,"",0,"",0,"",0,""],["% DPS Gain",8531,"0.5",17062,"1.0",25593,"1.5",34124,"2.0",42655,"2.5",51186,"3.0",59717,"3.5",68249,"4.0",76780,"4.5",85311,"5.0",0,"",0,"",0,"",0,"",0,"",0,"",0,"",0,"",0,"",0,"",0,"",0,"",0,"",0,"",0,"",0,"",0,""]]