[[{"type":"string"},{"type":"number"},{"type":"string"},{"type":"number"},{"type":"string"},{"type":"number"},{"type":"string"},{"type":"number"},{"type":"string"},{"type":"number"},{"type":"string"},{"type":"number"},{"type":"string"},{"type":"number"},{"type":"string"},{"type":"number"},{"type":"string"},{"type":"number"},{"type":"string"},{"type":"number"},{"type":"string"},{"type":"number"},{"type":"string"},{"type":"number"},{"type":"string"},{"type":"number"},{"type":"string"},{"type":"number"},{"type":"string"},{"type":"number"},{"type":"string"},{"type":"number"},{"type":"string"},{"type":"number"},{"type":"string"},{"type":"number"},{"type":"string"},{"type":"number"},{"type":"string"},{"type":"number"},{"type":"string"},{"type":"number"},{"type":"string"},{"type":"number"},{"type":"string"},{"type":"number"},{"type":"string"},{"type":"number"},{"type":"string"},{"type":"number"},{"type":"string"},{"type":"number"},{"type":"string"},{"type":"number"},{"type":"string"},{"type":"number"},{"type":"string"},{"type":"number"},{"type":"string"},{"type":"number"},{"type":"string"}],["Fortune's Bite",6176,"1",11554,"2",16804,"3",0,"",0,"",0,"",0,"",0,"",0,"",0,"",0,"",0,"",0,"",0,"",0,"",0,"",0,"",0,"",0,"",0,"",0,"",0,"",0,"",0,"",0,"",0,"",0,"",0,"",0,"",0,""],["Weapon Item Level",3205,"1",6410,"2",9617,"3",12645,"4",15673,"5",18702,"6",22011,"7",25320,"8",28631,"9",31672,"10",34713,"11",37755,"12",41152,"13",44549,"14",47947,"15",51319,"16",54691,"17",58065,"18",61948,"19",65831,"20",69715,"21",73246,"22",76777,"23",80310,"24",83999,"25",87688,"26",91379,"27",95033,"28",98687,"29",102343,"30"],["Shocklight",17829,"1",35820,"2",53393,"3",0,"",0,"",0,"",0,"",0,"",0,"",0,"",0,"",0,"",0,"",0,"",0,"",0,"",0,"",0,"",0,"",0,"",0,"",0,"",0,"",0,"",0,"",0,"",0,"",0,"",0,"",0,""],["Demon's Kiss",8067,"1",16205,"2",24271,"3",0,"",0,"",0,"",0,"",0,"",0,"",0,"",0,"",0,"",0,"",0,"",0,"",0,"",0,"",0,"",0,"",0,"",0,"",0,"",0,"",0,"",0,"",0,"",0,"",0,"",0,"",0,""],["Dark Sorrows",9739,"1",19064,"2",27906,"3",0,"",0,"",0,"",0,"",0,"",0,"",0,"",0,"",0,"",0,"",0,"",0,"",0,"",0,"",0,"",0,"",0,"",0,"",0,"",0,"",0,"",0,"",0,"",0,"",0,"",0,"",0,""],["Weak Point",25962,"1",52082,"2",78409,"3",0,"",0,"",0,"",0,"",0,"",0,"",0,"",0,"",0,"",0,"",0,"",0,"",0,"",0,"",0,"",0,"",0,"",0,"",0,"",0,"",0,"",0,"",0,"",0,"",0,"",0,"",0,""],["Soul Shadows",11386,"1",25981,"2",37356,"3",0,"",0,"",0,"",0,"",0,"",0,"",0,"",0,"",0,"",0,"",0,"",0,"",0,"",0,"",0,"",0,"",0,"",0,"",0,"",0,"",0,"",0,"",0,"",0,"",0,"",0,"",0,""],["Shadowbind",20520,"1",40887,"2",61007,"3",0,"",0,"",0,"",0,"",0,"",0,"",0,"",0,"",0,"",0,"",0,"",0,"",0,"",0,"",0,"",0,"",0,"",0,"",0,"",0,"",0,"",0,"",0,"",0,"",0,"",0,"",0,""],["Gutripper",17117,"1",33965,"2",50852,"3",0,"",0,"",0,"",0,"",0,"",0,"",0,"",0,"",0,"",0,"",0,"",0,"",0,"",0,"",0,"",0,"",0,"",0,"",0,"",0,"",0,"",0,"",0,"",0,"",0,"",0,"",0,""],["Murderous Intent",17458,"1",34558,"2",51875,"3",0,"",0,"",0,"",0,"",0,"",0,"",0,"",0,"",0,"",0,"",0,"",0,"",0,"",0,"",0,"",0,"",0,"",0,"",0,"",0,"",0,"",0,"",0,"",0,"",0,"",0,"",0,""],["The Quiet Knife",16837,"1",33436,"2",50493,"3",0,"",0,"",0,"",0,"",0,"",0,"",0,"",0,"",0,"",0,"",0,"",0,"",0,"",0,"",0,"",0,"",0,"",0,"",0,"",0,"",0,"",0,"",0,"",0,"",0,"",0,"",0,""],["Precision Strike",12180,"1",23148,"2",33670,"3",0,"",0,"",0,"",0,"",0,"",0,"",0,"",0,"",0,"",0,"",0,"",0,"",0,"",0,"",0,"",0,"",0,"",0,"",0,"",0,"",0,"",0,"",0,"",0,"",0,"",0,"",0,""],["Energetic Stabbing",28392,"1",55267,"2",81533,"3",0,"",0,"",0,"",0,"",0,"",0,"",0,"",0,"",0,"",0,"",0,"",0,"",0,"",0,"",0,"",0,"",0,"",0,"",0,"",0,"",0,"",0,"",0,"",0,"",0,"",0,"",0,""],["Chaotic Darkness",18049,"1",36389,"2",54975,"3",0,"",0,"",0,"",0,"",0,"",0,"",0,"",0,"",0,"",0,"",0,"",0,"",0,"",0,"",0,"",0,"",0,"",0,"",0,"",0,"",0,"",0,"",0,"",0,"",0,"",0,"",0,""],["Master of Shadows",14214,"1",28509,"2",42270,"3",0,"",0,"",0,"",0,"",0,"",0,"",0,"",0,"",0,"",0,"",0,"",0,"",0,"",0,"",0,"",0,"",0,"",0,"",0,"",0,"",0,"",0,"",0,"",0,"",0,"",0,"",0,""],["Torment the Weak",23157,"1",44599,"2",67515,"3",0,"",0,"",0,"",0,"",0,"",0,"",0,"",0,"",0,"",0,"",0,"",0,"",0,"",0,"",0,"",0,"",0,"",0,"",0,"",0,"",0,"",0,"",0,"",0,"",0,"",0,"",0,""],["Light Speed",14110,"1",27838,"2",41263,"3",0,"",0,"",0,"",0,"",0,"",0,"",0,"",0,"",0,"",0,"",0,"",0,"",0,"",0,"",0,"",0,"",0,"",0,"",0,"",0,"",0,"",0,"",0,"",0,"",0,"",0,"",0,""],["Secure in the Light",20768,"1",39879,"2",60251,"3",0,"",0,"",0,"",0,"",0,"",0,"",0,"",0,"",0,"",0,"",0,"",0,"",0,"",0,"",0,"",0,"",0,"",0,"",0,"",0,"",0,"",0,"",0,"",0,"",0,"",0,"",0,""],["Infusion of Light",20697,"1",40143,"2",59449,"3",0,"",0,"",0,"",0,"",0,"",0,"",0,"",0,"",0,"",0,"",0,"",0,"",0,"",0,"",0,"",0,"",0,"",0,"",0,"",0,"",0,"",0,"",0,"",0,"",0,"",0,"",0,""]]