[[{"type":"string"},{"type":"number"},{"type":"string"},{"type":"number"},{"type":"string"},{"type":"number"},{"type":"string"},{"type":"number"},{"type":"string"},{"type":"number"},{"type":"string"},{"type":"number"},{"type":"string"},{"type":"number"},{"type":"string"},{"type":"number"},{"type":"string"},{"type":"number"},{"type":"string"},{"type":"number"},{"type":"string"},{"type":"number"},{"type":"string"},{"type":"number"},{"type":"string"},{"type":"number"},{"type":"string"},{"type":"number"},{"type":"string"},{"type":"number"},{"type":"string"},{"type":"number"},{"type":"string"},{"type":"number"},{"type":"string"}],["Weapon Item Level",7055,"1",14110,"2",21165,"3",27536,"4",33907,"5",40278,"6",47148,"7",54018,"8",60889,"9",67921,"10",74953,"11",81986,"12",89659,"13",97332,"14",105005,"15",112506,"16",120007,"17"],["Shocklight",10395,"1",19161,"2",26646,"3",0,"",0,"",0,"",0,"",0,"",0,"",0,"",0,"",0,"",0,"",0,"",0,"",0,"",0,""],["Dark Sorrows",12052,"1",24540,"2",35889,"3",0,"",0,"",0,"",0,"",0,"",0,"",0,"",0,"",0,"",0,"",0,"",0,"",0,"",0,""],["Shadowbind",26303,"1",51962,"2",77276,"3",0,"",0,"",0,"",0,"",0,"",0,"",0,"",0,"",0,"",0,"",0,"",0,"",0,"",0,""],["Icy Caress",15850,"1",34193,"2",50199,"3",0,"",0,"",0,"",0,"",0,"",0,"",0,"",0,"",0,"",0,"",0,"",0,"",0,"",0,""],["Clarity of Thought",37941,"1",73115,"2",107522,"3",0,"",0,"",0,"",0,"",0,"",0,"",0,"",0,"",0,"",0,"",0,"",0,"",0,"",0,""],["Ice Age",18693,"1",36916,"2",54206,"3",0,"",0,"",0,"",0,"",0,"",0,"",0,"",0,"",0,"",0,"",0,"",0,"",0,"",0,""],["Obsidian Lance",18125,"1",35769,"2",53623,"3",0,"",0,"",0,"",0,"",0,"",0,"",0,"",0,"",0,"",0,"",0,"",0,"",0,"",0,""],["Let It Go",25667,"1",48998,"2",72627,"3",0,"",0,"",0,"",0,"",0,"",0,"",0,"",0,"",0,"",0,"",0,"",0,"",0,"",0,""],["Orbital Strike",3722,"1",6602,"2",9823,"3",0,"",0,"",0,"",0,"",0,"",0,"",0,"",0,"",0,"",0,"",0,"",0,"",0,"",0,""],["Frozen Veins",12886,"1",38296,"2",46000,"3",0,"",0,"",0,"",0,"",0,"",0,"",0,"",0,"",0,"",0,"",0,"",0,"",0,"",0,""],["Secure in the Light",26611,"1",51928,"2",79064,"3",0,"",0,"",0,"",0,"",0,"",0,"",0,"",0,"",0,"",0,"",0,"",0,"",0,"",0,""],["Light Speed",16088,"1",31493,"2",46882,"3",0,"",0,"",0,"",0,"",0,"",0,"",0,"",0,"",0,"",0,"",0,"",0,"",0,"",0,""],["Infusion of Light",26431,"1",52622,"2",77630,"3",0,"",0,"",0,"",0,"",0,"",0,"",0,"",0,"",0,"",0,"",0,"",0,"",0,"",0,""],["Chaotic Darkness",24156,"1",47672,"2",69901,"3",0,"",0,"",0,"",0,"",0,"",0,"",0,"",0,"",0,"",0,"",0,"",0,"",0,"",0,""],["Master of Shadows",12599,"1",24518,"2",36636,"3",0,"",0,"",0,"",0,"",0,"",0,"",0,"",0,"",0,"",0,"",0,"",0,"",0,"",0,""],["Murderous Intent",17869,"1",35351,"2",53603,"3",0,"",0,"",0,"",0,"",0,"",0,"",0,"",0,"",0,"",0,"",0,"",0,"",0,"",0,""],["Torment the Weak",28266,"1",56645,"2",84371,"3",0,"",0,"",0,"",0,"",0,"",0,"",0,"",0,"",0,"",0,"",0,"",0,"",0,"",0,""],["% DPS Gain",9122,"0.5",18244,"1.0",27366,"1.5",36488,"2.0",45610,"2.5",54732,"3.0",63854,"3.5",72976,"4.0",82098,"4.5",91220,"5.0",100342,"5.5",109464,"6.0",118586,"6.5",127708,"7.0",0,"",0,"",0,""]]